py.typed
exfunc_sdk/__init__.py
exfunc_sdk/_hooks/__init__.py
exfunc_sdk/_hooks/registration.py
exfunc_sdk/_hooks/sdkhooks.py
exfunc_sdk/_hooks/types.py
exfunc_sdk/_version.py
exfunc_sdk/basesdk.py
exfunc_sdk/google.py
exfunc_sdk/httpclient.py
exfunc_sdk/linkedin.py
exfunc_sdk/models/__init__.py
exfunc_sdk/models/get_business_reviewsop.py
exfunc_sdk/models/get_businessop.py
exfunc_sdk/models/get_companyop.py
exfunc_sdk/models/get_job_postingop.py
exfunc_sdk/models/get_personop.py
exfunc_sdk/models/get_price_historyop.py
exfunc_sdk/models/get_product_reviewsop.py
exfunc_sdk/models/get_productop.py
exfunc_sdk/models/get_propertyop.py
exfunc_sdk/models/get_taskop.py
exfunc_sdk/models/get_tweetop.py
exfunc_sdk/models/get_user_by_idop.py
exfunc_sdk/models/get_user_followersop.py
exfunc_sdk/models/get_user_tweetsop.py
exfunc_sdk/models/get_userop.py
exfunc_sdk/models/getuserfollowingsop.py
exfunc_sdk/models/googlenews.py
exfunc_sdk/models/googleproduct.py
exfunc_sdk/models/googleproductreview.py
exfunc_sdk/models/linkedincompany.py
exfunc_sdk/models/linkedinjobposting.py
exfunc_sdk/models/linkedinperson.py
exfunc_sdk/models/navigatortask.py
exfunc_sdk/models/run_taskop.py
exfunc_sdk/models/sdkerror.py
exfunc_sdk/models/search_businessesop.py
exfunc_sdk/models/search_companiesop.py
exfunc_sdk/models/search_job_postingsop.py
exfunc_sdk/models/search_newsop.py
exfunc_sdk/models/search_peopleop.py
exfunc_sdk/models/search_productsop.py
exfunc_sdk/models/search_propertiesop.py
exfunc_sdk/models/search_tweetsop.py
exfunc_sdk/models/search_usersop.py
exfunc_sdk/models/security.py
exfunc_sdk/models/servererror.py
exfunc_sdk/models/tweet.py
exfunc_sdk/models/twitteruser.py
exfunc_sdk/models/usererror.py
exfunc_sdk/models/yelpbusiness.py
exfunc_sdk/models/yelpreview.py
exfunc_sdk/models/zillowpricehistoryevent.py
exfunc_sdk/models/zillowproperty.py
exfunc_sdk/navigator.py
exfunc_sdk/py.typed
exfunc_sdk/sdk.py
exfunc_sdk/sdkconfiguration.py
exfunc_sdk/twitter.py
exfunc_sdk-0.3.1.dist-info/METADATA
exfunc_sdk-0.3.1.dist-info/WHEEL
exfunc_sdk-0.3.1.dist-info/RECORD
